<?xml version="1.0"?>

<form>
  <title>Parameters form</title>
  <row_length>4</row_length>
  <name>form</name>
  <action></action>
  <method>POST</method>
  <enctype></enctype>
  <encoding>UTF-8</encoding>
  <stored_encoding>ISO-8859-1</stored_encoding>
  <unicode_mode>false</unicode_mode>
  <i18n_domain></i18n_domain>
  <groups>
    <group>
      <title>Default</title>
      <fields>

      <field><id>google_calendar_account</id> <type>StringField</type>
        <values>
          <alternate_name></alternate_name>
          <css_class></css_class>
          <default>@GMail.com</default>
          <description>ID of your Google Calendar/Agenda account. eg: mycompany@gmail.com</description>
          <display_maxwidth></display_maxwidth>
          <display_width type="int">20</display_width>
          <enabled type="int">1</enabled>
          <external_validator></external_validator>
          <extra></extra>
          <hidden type="int">0</hidden>
          <max_length></max_length>
          <required type="int">1</required>
          <title>Google Calendar Account</title>
          <truncate type="int">0</truncate>
          <unicode type="int">0</unicode>
          <whitespace_preserve type="int">0</whitespace_preserve>
        </values>
        <tales>
        </tales>
        <messages>
          <message name="external_validator_failed">The input failed the external validator.</message>
          <message name="required_not_found">Input is required but no input given.</message>
          <message name="too_long">Too much input was given.</message>
        </messages>
      </field>
      <field><id>google_calendar_type</id> <type>RadioField</type>
        <values>
          <alternate_name></alternate_name>
          <css_class></css_class>
          <default>Month</default>
          <description>The type of google calendar to display</description>
          <enabled type="int">1</enabled>
          <external_validator></external_validator>
          <extra_item></extra_item>
          <first_item type="int">1</first_item>
          <hidden type="int">0</hidden>
          <items type="list">[('Month', 'MONTH'), ('Agenda', 'AGENDA')]</items>
          <orientation>vertical</orientation>
          <required type="int">1</required>
          <title>Google Calendar Type</title>
          <unicode type="int">0</unicode>
          <whitespace_preserve type="int">0</whitespace_preserve>
        </values>
        <tales>
        </tales>
        <messages>
          <message name="external_validator_failed">The input failed the external validator.</message>
          <message name="required_not_found">Input is required but no input given.</message>
          <message name="unknown_selection">You selected an item that was not in the list.</message>
        </messages>
      </field>
      <field><id>calendar_background_color</id> <type>StringField</type>
        <values>
          <alternate_name></alternate_name>
          <css_class></css_class>
          <default>FFFFFF</default>
          <description>Enter the six digits of the hexadecimal color code</description>
          <display_maxwidth type="int">6</display_maxwidth>
          <display_width type="int">20</display_width>
          <enabled type="int">1</enabled>
          <external_validator></external_validator>
          <extra></extra>
          <hidden type="int">0</hidden>
          <max_length></max_length>
          <required type="int">0</required>
          <title>Calendar Background Color</title>
          <truncate type="int">0</truncate>
          <unicode type="int">0</unicode>
          <whitespace_preserve type="int">0</whitespace_preserve>
        </values>
        <tales>
        </tales>
        <messages>
          <message name="external_validator_failed">The input failed the external validator.</message>
          <message name="required_not_found">Input is required but no input given.</message>
          <message name="too_long">Too much input was given.</message>
        </messages>
      </field>
      <field><id>calendar_title</id> <type>StringField</type>
        <values>
          <alternate_name></alternate_name>
          <css_class></css_class>
          <default>Google Calendar</default>
          <description>The title of the Google Calendar</description>
          <display_maxwidth></display_maxwidth>
          <display_width type="int">20</display_width>
          <enabled type="int">1</enabled>
          <external_validator></external_validator>
          <extra></extra>
          <hidden type="int">0</hidden>
          <max_length></max_length>
          <required type="int">1</required>
          <title>Calendar Title</title>
          <truncate type="int">0</truncate>
          <unicode type="int">0</unicode>
          <whitespace_preserve type="int">0</whitespace_preserve>
        </values>
        <tales>
        </tales>
        <messages>
          <message name="external_validator_failed">The input failed the external validator.</message>
          <message name="required_not_found">Input is required but no input given.</message>
          <message name="too_long">Too much input was given.</message>
        </messages>
      </field>
      <field><id>calendar_width</id> <type>IntegerField</type>
        <values>
          <alternate_name></alternate_name>
          <css_class></css_class>
          <default>640</default>
          <description>The width that the google calendar should have.</description>
          <display_maxwidth></display_maxwidth>
          <display_width type="int">20</display_width>
          <enabled type="int">1</enabled>
          <end></end>
          <external_validator></external_validator>
          <extra></extra>
          <hidden type="int">0</hidden>
          <required type="int">1</required>
          <start></start>
          <title>Calendar Width</title>
          <whitespace_preserve type="int">0</whitespace_preserve>
        </values>
        <tales>
        </tales>
        <messages>
          <message name="external_validator_failed">The input failed the external validator.</message>
          <message name="required_not_found">Input is required but no input given.</message>
          <message name="not_integer">You did not enter an integer.</message>
          <message name="integer_out_of_range">The integer you entered was out of range.</message>
        </messages>
      </field>
      <field><id>calendar_height</id> <type>IntegerField</type>
        <values>
          <alternate_name></alternate_name>
          <css_class></css_class>
          <default>614</default>
          <description>The height of the Google Calendar</description>
          <display_maxwidth></display_maxwidth>
          <display_width type="int">20</display_width>
          <enabled type="int">1</enabled>
          <end></end>
          <external_validator></external_validator>
          <extra></extra>
          <hidden type="int">0</hidden>
          <required type="int">1</required>
          <start></start>
          <title>Calendar Height</title>
          <whitespace_preserve type="int">0</whitespace_preserve>
        </values>
        <tales>
        </tales>
        <messages>
          <message name="external_validator_failed">The input failed the external validator.</message>
          <message name="required_not_found">Input is required but no input given.</message>
          <message name="not_integer">You did not enter an integer.</message>
          <message name="integer_out_of_range">The integer you entered was out of range.</message>
        </messages>
      </field>
      </fields>
    </group>
  </groups>
</form>
